LICENSE
README.md
setup.cfg
setup.py
mh_z19/__init__.py
mh_z19/__main__.py
mh_z19/pwm.py
mh_z19.egg-info/PKG-INFO
mh_z19.egg-info/SOURCES.txt
mh_z19.egg-info/dependency_links.txt
mh_z19.egg-info/requires.txt
mh_z19.egg-info/top_level.txt