Metadata-Version: 2.1
Name: mh-z19
Version: 3.1.7
Summary: mh-z19 CO2 concentration sensor library for All models of Raspberry Pi
Home-page: https://github.com/UedaTakeyuki/mh-z19
Author: Takeyuki UEDA
Author-email: gde00107@nifty.com
License: MIT
Keywords: sensor,IoT,Raspberry Pi,mh-z19,CO2
Classifier: Development Status :: 5 - Production/Stable
Classifier: Programming Language :: Python
Classifier: Topic :: Terminals
License-File: LICENSE
